docloudstuff/__init__.py
docloudstuff/events/__init__.py
docloudstuff/events/events.py
docloudstuff-0.1.9.4.dist-info/LICENSE
docloudstuff-0.1.9.4.dist-info/WHEEL
docloudstuff-0.1.9.4.dist-info/METADATA
docloudstuff-0.1.9.4.dist-info/RECORD
